{"backfaceCulling": false, "pivots": true, "displayTextures": false, "greasePencils": true, "displayLights": "default", "smoothWireframe": false, "sortTransparent": true, "grid": false, "fogColor": [0.5, 0.5, 0.5, 1.0], "nurbsSurfaces": true, "shadows": false, "clipGhosts": true, "smallObjectThreshold": -1.0, "textureAnisotropic": false, "nCloths": true, "useDefaultMaterial": false, "fogging": false, "nParticles": true, "rendererName": "vp2Renderer", "textureHilight": true, "dynamics": true, "subdivSurfaces": true, "bumpResolution": [512, 512], "displayAppearance": "smoothShaded", "textureSampling": 2, "cameras": true, "viewSelected": false, "fluids": true, "fogSource": "fragment", "xray": false, "lights": true, "nurbsCurves": true, "locators": true, "maximumNumHardwareLights": true, "textures": true, "selectionHiliteDisplay": true, "follicles": true, "hulls": true, "twoSidedLighting": false, "lineWidth": 1.0, "jointXray": false, "particleInstancers": true, "fogMode": "linear", "activeComponentsXray": false, "pluginShapes": true, "useBaseRenderer": false, "shadingModel": 0, "textureMaxSize": 16384, "textureDisplay": "modulate", "ikHandles": true, "handles": true, "cullingOverride": "none", "controlVertices": true, "fogDensity": 0.10000000149011612, "polymeshes": true, "depthOfField": false, "colorResolution": [256, 156], "isFiltered": false, "imagePlane": true, "objectFilterShowInHUD": true, "lowQualityLighting": false, "headsUpDisplay": true, "hairSystems": true, "planes": true, "ignorePanZoom": false, "smallObjectCulling": false, "manipulators": true, "joints": true, "transparencyAlgorithm": "frontAndBackCull", "dynamicConstraints": true, "occlusionCulling": false, "RenderGlobals": {"multiSampleEnable": true, "ssaoFilterRadius": 16, "colorBakeResolution": 64, "motionBlurEnable": true, "motionBlurSampleCount": 8, "ssaoRadius": 16, "bumpBakeResolution": 64, "ssaoAmount": 1.0, "multiSampleCount": 8, "ssaoSamples": 16, "ssaoEnable": true}, "deformers": true, "motionTrails": true, "useReducedRenderer": false, "textureCompression": false, "fogStart": 0.0, "activeOnly": false, "interactiveBackFaceCull": false, "gpuCacheDisplayFilter": true, "strokes": true, "camera": "persp", "bufferMode": "double", "nRigids": true, "interactiveDisableShadows": false, "wireframeOnShaded": true, "dimensions": true, "fogEnd": 100.0, "maxConstantTransparency": 1.0, "transpInShadows": false, "useInteractiveMode": false}